pipe_strip/__init__.py
pipe_strip/auto_restart.py
pipe_strip/pipe_strip.py
pipe_strip/resources/pipe_strip_mega_v1.ans
pipe_strip/resources/pipe_strip_micro_v1.ans
pipe_strip/resources/pipe_strip_mini_alt_alt_alt_alt_alt_text.ans
pipe_strip/resources/pipe_strip_mini_alt_alt_alt_alt_text.ans
pipe_strip/resources/pipe_strip_mini_alt_alt_alt_text.ans
pipe_strip/resources/pipe_strip_mini_alt_alt_text.ans
pipe_strip/resources/pipe_strip_mini_alt_text.ans
pipe_strip/resources/pipe_strip_mini_v1.ans
pipe_strip/resources/pipe_strip_mini_v2.ans
pipe_strip/resources/pipe_strip_sequel_micro_v1.ans
pipe_strip/resources/pipe_strip_sequel_micro_v2.ans
pipe_strip/resources/pipe_strip_sequel_micro_v3.ans
pipe_strip/resources/pipe_strip_sequel_micro_v4.ans
pipe_strip/resources/pipe_strip_sequel_mini_v1.ans
pipe_strip/resources/pipe_strip_sequel_v1.ans
pipe_strip/resources/pipe_strip_sequel_v2.ans
pipe_strip/resources/pipe_strip_sequel_v3.ans
pipe_strip/resources/pipe_strip_sequel_v4.ans
pipe_strip/resources/pipe_strip_sequel_v5.ans
pipe_strip/resources/pipe_strip_sequel_v6.ans
pipe_strip/resources/pipe_strip_sequel_v7.ans
pipe_strip/resources/pipe_strip_v0.ans
pipe_strip/resources/pipe_strip_v1.ans
pipe_strip/resources/pipe_strip_v10.ans
pipe_strip/resources/pipe_strip_v11.1_BAD_EARS.ans
pipe_strip/resources/pipe_strip_v11.ans
pipe_strip/resources/pipe_strip_v12.ans
pipe_strip/resources/pipe_strip_v12_tiling_v1.ans
pipe_strip/resources/pipe_strip_v12_tiling_v2.ans
pipe_strip/resources/pipe_strip_v12_tiling_v3.ans
pipe_strip/resources/pipe_strip_v2.ans
pipe_strip/resources/pipe_strip_v3.ans
pipe_strip/resources/pipe_strip_v4.ans
pipe_strip/resources/pipe_strip_v5.ans
pipe_strip/resources/pipe_strip_v6.ans
pipe_strip/resources/pipe_strip_v7.ans
pipe_strip/resources/pipe_strip_v8.ans
pipe_strip/resources/pipe_strip_v9.ans
pipe_strip-0.1.0.dist-info/LICENSE-CC0.txt
pipe_strip-0.1.0.dist-info/METADATA
pipe_strip-0.1.0.dist-info/WHEEL
pipe_strip-0.1.0.dist-info/entry_points.txt
pipe_strip-0.1.0.dist-info/top_level.txt
pipe_strip-0.1.0.dist-info/RECORD
