Metadata-Version: 2.1
Name: pipe-strip
Version: 0.1.0
Summary: A terminal-based comic reader for the Garfield comic strip
Home-page: https://github.com/1j01/pipe-strip
Author: Isaiah Odhner
Author-email: isaiahodhner@gmail.com
License: CC0-1.0
Keywords: tui,terminal,drawing,art,graphics,text,textual,rich,ansi,ansi-art,smoking,cat,jon,arbuckle,jim,davis,pipe,comic,comic-reader,garfield,immortality,pipe-strip,7-27
Classifier: Environment :: Console
Classifier: Intended Audience :: End Users/Desktop
Classifier: License :: CC0 1.0 Universal (CC0 1.0) Public Domain Dedication
Classifier: Development Status :: 3 - Alpha
Classifier: Operating System :: OS Independent
Classifier: Programming Language :: Python :: 3
Classifier: Topic :: Artistic Software
Classifier: Topic :: Multimedia :: Graphics :: Viewers
Classifier: Topic :: Terminals
Classifier: Natural Language :: English
License-File: LICENSE-CC0.txt
Requires-Dist: textual (==0.27.0)
Requires-Dist: rich (==13.3.5)
Provides-Extra: dev
Requires-Dist: watchdog (==3.0.0) ; extra == 'dev'
Requires-Dist: psutil (==5.9.0) ; extra == 'dev'
Requires-Dist: types-psutil (==5.9.5.15) ; extra == 'dev'
